<?xml version="1.0" encoding="utf-8"?>
<Containers>
<Plugin>True</Plugin>
<PluginURL>https://raw.githubusercontent.com/ljm42/unraid-upnp/master/plugins/upnp-monitor.plg</PluginURL>
<PluginAuthor>ljm42</PluginAuthor>
<Beta>False</Beta>
<Category>Network:Management Network:Other</Category>
<Name>UPnP Monitor</Name>
<Description>
Gives visibility into the UPnP activity on your network
</Description>
<Support>https://forums.unraid.net/topic/86928-plugin-upnp-monitor/</Support>
<Icon>https://raw.githubusercontent.com/ljm42/unraid-upnp/master/source/upnp-monitor/usr/local/emhttp/plugins/upnp-monitor/upnp-monitor.png</Icon>
</Containers>
